{
  "minecraft:recipes/transportation/dark_oak_boat": {
    "criteria": {
      "entered_water": "2025-02-07 22:35:21 +0800"
    },
    "done": true
  },
  "minecraft:recipes/transportation/birch_boat": {
    "criteria": {
      "entered_water": "2025-02-07 22:35:21 +0800"
    },
    "done": true
  },
  "cfm:install": {
    "criteria": {
      "tick": "2025-02-07 22:28:53 +0800"
    },
    "done": true
  },
  "minecraft:recipes/transportation/acacia_boat": {
    "criteria": {
      "entered_water": "2025-02-07 22:35:21 +0800"
    },
    "done": true
  },
  "astralsorcery:root": {
    "criteria": {
      "astralsorcery_present": "2025-02-07 22:28:53 +0800"
    },
    "done": true
  },
  "galacticraftcore:galacticraft/root": {
    "criteria": {
      "tick": "2025-02-07 22:28:53 +0800"
    },
    "done": true
  },
  "minecraft:recipes/transportation/boat": {
    "criteria": {
      "entered_water": "2025-02-07 22:35:21 +0800"
    },
    "done": true
  },
  "minecraft:recipes/transportation/jungle_boat": {
    "criteria": {
      "entered_water": "2025-02-07 22:35:21 +0800"
    },
    "done": true
  },
  "minecraft:recipes/misc/bowl": {
    "criteria": {
      "has_brown_mushroom": "2025-02-07 22:34:32 +0800"
    },
    "done": true
  },
  "cfm:root": {
    "criteria": {
      "tick": "2025-02-07 22:28:53 +0800"
    },
    "done": true
  },
  "minecraft:recipes/transportation/spruce_boat": {
    "criteria": {
      "entered_water": "2025-02-07 22:35:21 +0800"
    },
    "done": true
  },
  "twilightforest:alt/compat/tconstruct": {
    "criteria": {
      "book": "2025-02-07 22:28:52 +0800"
    },
    "done": true
  },
  "minecraft:adventure/adventuring_time": {
    "criteria": {
      "swampland": "2025-02-07 22:31:57 +0800",
      "river": "2025-02-07 22:31:56 +0800"
    },
    "done": false
  }
}